radifox/convert/__init__.py
radifox/convert/_static_version.py
radifox/convert/_version.py
radifox/convert/base.py
radifox/convert/cli.py
radifox/convert/dicom.py
radifox/convert/exec.py
radifox/convert/lut.py
radifox/convert/metadata.py
radifox/convert/nib_parrec_fork.py
radifox/convert/parrec.py
radifox/convert/parrec_writer.py
radifox/convert/utils.py
radifox/convert/parrec_templates/gen_info.txt
radifox/convert/parrec_templates/pixel_values.txt
radifox/convert/parrec_templates/top_header.txt
radifox_convert-1.1.0.dist-info/LICENSE
radifox_convert-1.1.0.dist-info/METADATA
radifox_convert-1.1.0.dist-info/WHEEL
radifox_convert-1.1.0.dist-info/entry_points.txt
radifox_convert-1.1.0.dist-info/top_level.txt
radifox_convert-1.1.0.dist-info/RECORD
