Metadata-Version: 2.1
Name: radifox-convert
Version: 1.1.0
Summary: A quality assurance webapp for the RADIFOX framework.
Author-email: JH-MIPC <jhmipc@jh.edu>
License: Apache-2.0
Project-URL: Homepage, https://github.com/jh-mipc/radifox-convert
Classifier: Programming Language :: Python :: 3
Classifier: License :: OSI Approved :: Apache Software License
Classifier: Operating System :: OS Independent
Requires-Python: >=3.10
License-File: LICENSE
Requires-Dist: nibabel
Requires-Dist: numpy
Requires-Dist: radifox >=2.1.0
Requires-Dist: pydicom
